cuttlery/__init__.py
cuttlery/calculate_pi.py
cuttlery/codon_dirichlet_test.py
cuttlery/codonfunctions.py
cuttlery/codonplot.py
cuttlery/cuttlery_main.py
cuttlery/forlooptest.py
cuttlery/heterogeneity.py
cuttlery/piNpiSsim.py
cuttlery/rcparams.py
cuttlery/version.py
cuttlery/test/__init__.py
cuttlery/test/test_codonfunctions.py
cuttlery-0.1614.dist-info/DESCRIPTION.rst
cuttlery-0.1614.dist-info/METADATA
cuttlery-0.1614.dist-info/RECORD
cuttlery-0.1614.dist-info/WHEEL
cuttlery-0.1614.dist-info/entry_points.txt
cuttlery-0.1614.dist-info/metadata.json
cuttlery-0.1614.dist-info/top_level.txt
